syn_apse/__init__.py
syn_apse/cli.py
syn_apse/core/__init__.py
syn_apse/core/engine.py
syn_apse/manipulation/__init__.py
syn_apse/manipulation/http_modifier.py
syn_apse/modules/__init__.py
syn_apse/modules/arp_spoofer.py
syn_apse/modules/dns_server.py
syn_apse/modules/dns_spoofer.py
syn_apse/modules/sniffer.py
syn_apse/utils/__init__.py
syn_apse/utils/network.py
synapse_toolkit-1.0.0.dist-info/METADATA
synapse_toolkit-1.0.0.dist-info/WHEEL
synapse_toolkit-1.0.0.dist-info/entry_points.txt
synapse_toolkit-1.0.0.dist-info/top_level.txt
synapse_toolkit-1.0.0.dist-info/RECORD
