Metadata-Version: 2.4
Name: synapse-toolkit
Version: 1.0.0
Summary: A modular Man-in-the-Middle (MitM) toolkit for network analysis.
Home-page: https://github.com/kalandjl/SYNapse
Author: Kalan Jarvis-Loewen
Classifier: Development Status :: 3 - Alpha
Classifier: Intended Audience :: Developers
Classifier: Topic :: Security
Classifier: License :: OSI Approved :: MIT License
Classifier: Programming Language :: Python :: 3
Classifier: Programming Language :: Python :: 3.8
Classifier: Programming Language :: Python :: 3.9
Classifier: Programming Language :: Python :: 3.10
Requires-Python: >=3.8
Requires-Dist: scapy
Requires-Dist: NetfilterQueue; platform_system == "Linux"
Dynamic: author
Dynamic: classifier
Dynamic: description
Dynamic: description-content-type
Dynamic: home-page
Dynamic: requires-dist
Dynamic: requires-python
Dynamic: summary
